odoo8_addon_l10n_eu_nace-8.0.2.1.0.99.dev4-nspkg.pth
odoo_addons/l10n_eu_nace/README.rst
odoo_addons/l10n_eu_nace/__init__.py
odoo_addons/l10n_eu_nace/__openerp__.py
odoo_addons/l10n_eu_nace/partner.py
odoo_addons/l10n_eu_nace/partner_view.xml
odoo_addons/l10n_eu_nace/data/NACE_REV2_bg.csv
odoo_addons/l10n_eu_nace/data/NACE_REV2_cs.csv
odoo_addons/l10n_eu_nace/data/NACE_REV2_da.csv
odoo_addons/l10n_eu_nace/data/NACE_REV2_de.csv
odoo_addons/l10n_eu_nace/data/NACE_REV2_el.csv
odoo_addons/l10n_eu_nace/data/NACE_REV2_en.csv
odoo_addons/l10n_eu_nace/data/NACE_REV2_es.csv
odoo_addons/l10n_eu_nace/data/NACE_REV2_et.csv
odoo_addons/l10n_eu_nace/data/NACE_REV2_fi.csv
odoo_addons/l10n_eu_nace/data/NACE_REV2_fr.csv
odoo_addons/l10n_eu_nace/data/NACE_REV2_hr.csv
odoo_addons/l10n_eu_nace/data/NACE_REV2_hu.csv
odoo_addons/l10n_eu_nace/data/NACE_REV2_it.csv
odoo_addons/l10n_eu_nace/data/NACE_REV2_lt.csv
odoo_addons/l10n_eu_nace/data/NACE_REV2_lv.csv
odoo_addons/l10n_eu_nace/data/NACE_REV2_mt.csv
odoo_addons/l10n_eu_nace/data/NACE_REV2_nl.csv
odoo_addons/l10n_eu_nace/data/NACE_REV2_no.csv
odoo_addons/l10n_eu_nace/data/NACE_REV2_pl.csv
odoo_addons/l10n_eu_nace/data/NACE_REV2_pt.csv
odoo_addons/l10n_eu_nace/data/NACE_REV2_ro.csv
odoo_addons/l10n_eu_nace/data/NACE_REV2_ru.csv
odoo_addons/l10n_eu_nace/data/NACE_REV2_sk.csv
odoo_addons/l10n_eu_nace/data/NACE_REV2_sl.csv
odoo_addons/l10n_eu_nace/data/NACE_REV2_sv.csv
odoo_addons/l10n_eu_nace/data/NACE_REV2_tr.csv
odoo_addons/l10n_eu_nace/data/make_data.py
odoo_addons/l10n_eu_nace/data/res.partner.category.csv
odoo_addons/l10n_eu_nace/i18n/bg.po
odoo_addons/l10n_eu_nace/i18n/cs.po
odoo_addons/l10n_eu_nace/i18n/da.po
odoo_addons/l10n_eu_nace/i18n/de.po
odoo_addons/l10n_eu_nace/i18n/el.po
odoo_addons/l10n_eu_nace/i18n/et.po
odoo_addons/l10n_eu_nace/i18n/fi.po
odoo_addons/l10n_eu_nace/i18n/fr.po
odoo_addons/l10n_eu_nace/i18n/hr.po
odoo_addons/l10n_eu_nace/i18n/hu.po
odoo_addons/l10n_eu_nace/i18n/it.po
odoo_addons/l10n_eu_nace/i18n/lt.po
odoo8_addon_l10n_eu_nace-8.0.2.1.0.99.dev4.dist-info/METADATA
odoo8_addon_l10n_eu_nace-8.0.2.1.0.99.dev4.dist-info/WHEEL
odoo8_addon_l10n_eu_nace-8.0.2.1.0.99.dev4.dist-info/namespace_packages.txt
odoo8_addon_l10n_eu_nace-8.0.2.1.0.99.dev4.dist-info/top_level.txt
odoo8_addon_l10n_eu_nace-8.0.2.1.0.99.dev4.dist-info/RECORD
